{
  "posts": [
    {
      "booped": true,
      "date": "September 7th, 2024",
      "html": "msg-delta.html",
      "replies": [],
      "tags": [
        "#gaming",
        "#metalgear",
        "#shitpost"
      ]
    },
    {
      "booped": false,
      "date": "August 27th, 2024",
      "html": "cool-gundam.html",
      "replies": [],
      "tags": [
        "#gundam",
        "#gunpla"
      ]
    },
    {
      "booped": false,
      "date": "August 8th, 2024",
      "html": "new-gunpla.html",
      "replies": [],
      "tags": ["#gundam",
        "#gunpla"]
    },
    {
      "booped": false,
      "date": "August 1st, 2024",
      "html": "anime-dance.html",
      "replies": [],
      "tags": ["#anime"]
    },
    {
      "booped": false,
      "date": "July 18th, 2024",
      "html": "berserk-watch.html",
      "replies": [],
      "tags": ["#anime"]
    },
    {
      "booped": false,
      "date": "June 27th, 2024",
      "html": "lake-of-rot.html",
      "replies": [],
      "tags": ["eldenring", "#gaming", "#shitpost"]
    },
    {
      "booped": false,
      "date": "May 22nd, 2024",
      "html": "elden-ring-str.html",
      "replies": [],
      "tags": ["eldenring", "#gaming"]
    },
    {
      "booped": false,
      "date": "May 18th, 2024",
      "html": "new-kit.html",
      "replies": [],
      "tags": ["#drumming"]
    },
    {
      "booped": false,
      "date": "May 14th, 2024",
      "html": "good-med-news.html",
      "replies": [],
      "tags": ["#gg"]
    },
    {
      "booped": false,
      "date": "April 27th, 2024",
      "html": "lunar.html",
      "replies": [],
      "tags": ["#anime", "#gaming", "#psx"]
    },
    {
      "booped": false,
      "date": "April 20th, 2024",
      "html": "no-weed.html",
      "replies": [],
      "tags": ["#weed"]
    },
    {
      "booped": false,
      "date": "April 12th, 2024",
      "html": "godzilla-and-me.html",
      "replies": [],
      "tags": ["#godzilla"]
    },
    {
      "booped": false,
      "date": "April 9th, 2024",
      "html": "godzilla-kick.html",
      "replies": [],
      "tags": ["#godzilla", "#shitpost"]
    },
    {
      "booped": false,
      "date": "May 11th, 2024",
      "html": "me-a-drummer.html",
      "replies": [],
      "tags": ["#drumming"]
    },
    {
      "booped": false,
      "date": "May 7th, 2024",
      "html": "dale-cooper.html",
      "replies": [],
      "tags": ["#shitpost", "#twinpeaks"]
    },
    {
      "booped": false,
      "date": "January 2nd, 2024",
      "html": "bi-mohawk.html",
      "replies": [],
      "tags": ["#shitpost"]
    },
    {
      "booped": false,
      "date": "December 27th, 2023",
      "html": "alan-100.html",
      "replies": [],
      "tags": ["#alanwake", "#gaming"]
    },
    {
      "booped": false,
      "date": "December 20th, 2023",
      "html": "anxiety-day.html",
      "replies": [],
      "tags": ["#anxiety"]
    },
    {
      "booped": false,
      "date": "December 17th, 2023",
      "html": "starcraft.html",
      "replies": [],
      "tags": ["#gaming", "#memories"]
    },
    {
      "booped": false,
      "date": "December 9th, 2023",
      "html": "anime-vibes.html",
      "replies": [],
      "tags": ["#anime"]
    },
    {
      "booped": false,
      "date": "November 29th, 2023",
      "html": "dusty-kit.html",
      "replies": [],
      "tags": ["#drumming"]
    },
    {
      "booped": false,
      "date": "November 26th, 2023",
      "html": "alan-wake-2.html",
      "replies": [],
      "tags": ["#alanwake", "#gaming"]
    },
    {
      "booped": false,
      "date": "November 20th, 2023",
      "html": "anime-gun.html",
      "replies": [],
      "tags": ["#anime"]
    },
    {
      "booped": false,
      "date": "November 15th, 2023",
      "html": "mgs-pixel.html",
      "replies": [],
      "tags": ["#gaming", "#metalgear","#memories"]
    },
    {
      "booped": false,
      "date": "November 11th, 2023",
      "html": "mortal-movie.html",
      "replies": [],
      "tags": ["#shitpost"]
    },
    {
      "booped": false,
      "date": "November 2nd, 2023",
      "html": "bubblegum.html",
      "replies": [],
      "tags": ["#anime"]
    },
    {
      "booped": false,
      "date": "October 30th, 2023",
      "html": "anime-hand.html",
      "replies": [],
      "tags": ["#anime"]
    },
    {
      "booped": false,
      "date": "October 29th, 2023",
      "html": "drop-power.html",
      "replies": [],
      "tags": ["#shitpost"]
    },
    {
      "booped": false,
      "date": "October 16th, 2023",
      "html": "dank.html",
      "replies": [],
      "tags": ["#shitpost", "#weed"]
    },
    {
      "booped": false,
      "date": "October 8th, 2023",
      "html": "monster-squad.html",
      "replies": [],
      "tags": ["#horror", "#memories"]
    },
    {
      "booped": false,
      "date": "October 6th, 2023",
      "html": "ghostwatch.html",
      "replies": [],
      "tags": ["#horror"]
    },
    {
      "booped": false,
      "date": "October 4th, 2023",
      "html": "wake-date.html",
      "replies": [],
      "tags": ["#alanwake", "#gaming"]
    },
    {
      "booped": false,
      "date": "September 21st, 2023",
      "html": "doinks.html",
      "replies": [],
      "tags": ["#shitpost", "#weed"]
    },
    {
      "booped": false,
      "date": "September 19th, 2023",
      "html": "daydream.html",
      "replies": [],
      "tags": ["#memories"]
    },
    {
      "booped": false,
      "date": "September 1st, 2023",
      "html": "fight-stick.html",
      "replies": [],
      "tags": ["#gaming"]
    },
    {
      "booped": false,
      "date": "August 30th, 2023",
      "html": "band-sad.html",
      "replies": [],
      "tags": ["#memories"]
    },
    {
      "booped": false,
      "date": "August 21st, 2023",
      "html": "spider.html",
      "replies": [],
      "tags": ["#shitpost"]
    },
    {
      "booped": false,
      "date": "August 19th, 2023",
      "html": "death-stranding.html",
      "replies": [],
      "tags": ["#gaming"]
    },
    {
      "booped": false,
      "date": "August 18th, 2023",
      "html": "anime-rise.html",
      "replies": [],
      "tags": ["#anime"]
    },
    {
      "booped": false,
      "date": "August 13th, 2023",
      "html": "cutie-honey.html",
      "replies": [],
      "tags": ["#anime","#memories"]
    },
    {
      "booped": false,
      "date": "August 3rd, 2023",
      "html": "wizards.html",
      "replies": [],
      "tags": ["#memories"]
    },
    {
      "booped": false,
      "date": "August 1st, 2023",
      "html": "astarion.html",
      "replies": [],
      "tags": ["#gaming"]
    },
    {
      "booped": false,
      "date": "July 27th, 2023",
      "html": "big-hug.html",
      "replies": [],
      "tags": ["#shitpost"]
    },
    {
      "booped": false,
      "date": "July 20th, 2023",
      "html": "ico.html",
      "replies": [],
      "tags": ["#gaming", "#memories"]
    },
    {
      "booped": false,
      "date": "July 17th, 2023",
      "html": "ocelot.html",
      "replies": [],
      "tags": ["#gaming", "#metalgear"]
    },
    {
      "booped": false,
      "date": "July 1st, 2023",
      "html": "wiff.html",
      "replies": [],
      "tags": ["#sad"]
    },
    {
      "booped": false,
      "date": "June 17th, 2023",
      "html": "biker-mice.html",
      "replies": [],
      "tags": ["#shitpost"]
    }
  ]
}
